haiguitang_mcp/__init__.py
haiguitang_mcp/__main__.py
haiguitang_mcp/server.py
haiguitang_mcp/puzzles/忠诚的狗.md
haiguitang_mcp-0.1.2.dist-info/METADATA
haiguitang_mcp-0.1.2.dist-info/WHEEL
haiguitang_mcp-0.1.2.dist-info/entry_points.txt
haiguitang_mcp-0.1.2.dist-info/top_level.txt
haiguitang_mcp-0.1.2.dist-info/RECORD
