Metadata-Version: 2.4
Name: haiguitang-mcp
Version: 0.1.2
Summary: 海龟汤游戏的mcp服务
Requires-Python: >=3.12
Requires-Dist: mcp[cli]>=1.6.0
